miepy/cli.py
miepy/cluster.py
miepy/constants.py
miepy/coordinates.py
miepy/cpp.cp312-win_amd64.pyd
miepy/flux.py
miepy/forces.py
miepy/interactions.py
miepy/interface.py
miepy/special_functions.py
miepy/sphere_cluster.py
miepy/symmetry.py
miepy/utils.py
miepy/__init__.py
miepy/bin/mie_calculator
miepy/bin/tmatrix.exe
miepy/examples/01_dielectric_sphere.py
miepy/examples/02_ag_sphere.py
miepy/examples/03_ag_shell.py
miepy/examples/04_vary_index.py
miepy/examples/05_fields.py
miepy/examples/06_dimer_scattering.py
miepy/examples/07_dimer_force.py
miepy/examples/08_far_field.py
miepy/examples/09_whispering_gallery.py
miepy/examples/10_focused_gaussian.py
miepy/examples/11_imaging.py
miepy/examples/flux.py
miepy/examples/full.py
miepy/examples/gmt_single.py
miepy/examples/non-rec.py
miepy/examples/__init__.py
miepy/examples/benchmarks/cpp.py
miepy/examples/benchmarks/sphere_chain.py
miepy/examples/benchmarks/timer.py
miepy/examples/benchmarks/tmatrix_chain.py
miepy/examples/benchmarks/parallel/main.py
miepy/examples/benchmarks/parallel/run.sh
miepy/examples/benchmarks/parallel/timer.py
miepy/examples/benchmarks/parallel/view.py
miepy/examples/dev/fft_source.py
miepy/examples/fdtd_compare/cube_dimer_forces.py
miepy/examples/fdtd_compare/cube_near_fields.py
miepy/examples/fdtd_compare/cube_scattering.py
miepy/examples/fdtd_compare/cylinder_grid_forces_dielectric.py
miepy/examples/fdtd_compare/cylinder_grid_forces_gold.py
miepy/examples/fdtd_compare/cylinder_grid_scattering.py
miepy/examples/fdtd_compare/ellipsoid_scattering.py
miepy/examples/fdtd_compare/triangle_scattering.py
miepy/examples/tests/analytic_forces.py
miepy/examples/tests/cruzan.py
miepy/examples/tests/dipole.py
miepy/examples/tests/expand_beam.py
miepy/examples/tests/flux.py
miepy/examples/tests/incident_expansion.py
miepy/examples/tests/maxwell.py
miepy/examples/tests/pi_tau.py
miepy/examples/tests/vsh_orthogonality.py
miepy/examples/tests/vsh_translation.py
miepy/materials/database.zip
miepy-1.0.2.dist-info/DELVEWHEEL
miepy-1.0.2.dist-info/entry_points.txt
miepy-1.0.2.dist-info/METADATA
miepy-1.0.2.dist-info/RECORD
miepy-1.0.2.dist-info/WHEEL
miepy-1.0.2.dist-info/licenses/LICENSE.md
