Metadata-Version: 2.2
Name: miepy
Version: 1.0.2
Summary: Solve Maxwell's equations for a cluster of particles using the generalized multiparticle Mie theory (GMMT)
Keywords: electrodynamics,mie,scattering
Author-Email: John Parker <johnaparker@users.noreply.github.com>
License: GPLv3
Classifier: License :: OSI Approved :: GNU General Public License v3 (GPLv3)
Classifier: Programming Language :: Python
Classifier: Programming Language :: C++
Classifier: Programming Language :: Fortran
Classifier: Operating System :: Unix
Classifier: Operating System :: POSIX
Classifier: Operating System :: MacOS
Classifier: Operating System :: Microsoft :: Windows
Classifier: Development Status :: 3 - Alpha
Classifier: Topic :: Scientific/Engineering :: Physics
Classifier: Intended Audience :: Science/Research
Requires-Python: >=3.11
Requires-Dist: matplotlib>=3.10.7
Requires-Dist: numpy>=2.3.3
Requires-Dist: numpy-quaternion>=2024.0.12
Requires-Dist: pandas>=2.3.3
Requires-Dist: pyyaml>=6.0.3
Requires-Dist: scipy>=1.16.2
Requires-Dist: spherical>=1.0.18
Requires-Dist: sympy>=1.14.0
Requires-Dist: tqdm>=4.67.1
Requires-Dist: vpython>=7.6.5
